.cruft.json
MANIFEST.in
README.rst
pyproject.toml
setup.py
tox.ini
docs/Makefile
docs/conf.py
docs/index.rst
docs/make.bat
gildas_uvfit/__init__.py
gildas_uvfit/_version.py
gildas_uvfit/specutils_custom_loader.py
gildas_uvfit/table_io.py
gildas_uvfit/version.py
gildas_uvfit.egg-info/PKG-INFO
gildas_uvfit.egg-info/SOURCES.txt
gildas_uvfit.egg-info/dependency_links.txt
gildas_uvfit.egg-info/not-zip-safe
gildas_uvfit.egg-info/requires.txt
gildas_uvfit.egg-info/top_level.txt
gildas_uvfit/data/README.rst
gildas_uvfit/data/uvfit.fits
gildas_uvfit/tests/__init__.py
gildas_uvfit/tests/test_table_io.py
licenses/LICENSE.rst
licenses/README.rst
licenses/TEMPLATE_LICENSE.rst