Metadata-Version: 2.1
Name: gildas_uvfit
Version: 0.1
Summary: Helper function to read IRAM GILDAS uvfit fits file
Author-email: Alexandre Beelen <alexandre.beelen@lam.fr>
License: Copyright (c) 2024, Alexandre Beelen
Project-URL: repository, https://github.com/abeelen/gildas-uvfit
Requires-Python: >=3.9
Requires-Dist: astropy>=4.0
Requires-Dist: numpy>=1.16
Provides-Extra: test
Requires-Dist: pytest; extra == "test"
Requires-Dist: pytest-doctestplus; extra == "test"
Requires-Dist: pytest-cov; extra == "test"
Requires-Dist: specutils; extra == "test"
Provides-Extra: docs
Requires-Dist: sphinx; extra == "docs"
Requires-Dist: sphinx-automodapi; extra == "docs"
Provides-Extra: specutils
Requires-Dist: specutils; extra == "specutils"
